LICENSE
MANIFEST.in
README.rst
ebas_uploader.py
setup.py
ebas_uploader.egg-info/PKG-INFO
ebas_uploader.egg-info/SOURCES.txt
ebas_uploader.egg-info/dependency_links.txt
ebas_uploader.egg-info/entry_points.txt
ebas_uploader.egg-info/not-zip-safe
ebas_uploader.egg-info/requires.txt
ebas_uploader.egg-info/top_level.txt