Metadata-Version: 1.1
Name: ebas-uploader
Version: 0.2
Summary: a command line utility to watch a folder and auto-upload files to an EBAS node
Home-page: https://github.com/maizeanalyticsorg/ebas-uploader
Author: Maize Analytics
Author-email: UNKNOWN
License: MIT
Platform: UNKNOWN
Classifier: Development Status :: 4 - Beta
Classifier: License :: OSI Approved :: MIT License
Classifier: Operating System :: OS Independent
Classifier: Programming Language :: Python
Classifier: Topic :: Software Development :: Libraries :: Python Modules
